iidxdemo/__init__.py
iidxdemo/main.py
iidxdemo/cfg/version.txt
iidxdemo/clis/__init__.py
iidxdemo/clis/cli.py
iidxdemo-1.0.21.data/scripts/iidxdemo.sub.sh
iidxdemo-1.0.21.dist-info/METADATA
iidxdemo-1.0.21.dist-info/WHEEL
iidxdemo-1.0.21.dist-info/entry_points.txt
iidxdemo-1.0.21.dist-info/top_level.txt
iidxdemo-1.0.21.dist-info/RECORD
